{
  "title": "Направи го едро",
  "testCase": "Обгради ли името в <h1> и </h1>?",
  "blocks.0.text": "Името ти е там, но е дребно. Стои като случайна дума насред бял лист. А ти искаш да е заглавие — едро, дебело, важно.",
  "blocks.1.text": "Първо опитай сам",
  "blocks.2.text": "Пробвай да го увеличиш. Сериозно, опитай. Няма да успееш — и точно това е смисълът.",
  "blocks.3.text": "Няма как да напишеш „направи го голямо\". Няма бутон за шрифт. Няма къде да натиснеш. Празният текст просто си стои.",
  "blocks.4.text": "Ето инструментът",
  "blocks.5.text": "Обграждаш текста от двете страни. Отпред слагаш <h1>, отзад </h1>. Наклонената черта в края казва „тук свършва\".",
  "blocks.7.text": "Направи го и пусни. Името става едро и дебело.",
  "blocks.8.text": "Забележи какво НЕ направи: не избра шрифт, не каза колко голямо, не пипна цвят. Само каза „това е заглавие\". Останалото го реши браузърът."
}
